log_request_id/__init__.py
log_request_id/flask.py
log_request_id/logging.py
log_request_id/request_id.py
log_request_id-0.1.1.dist-info/LICENSE
log_request_id-0.1.1.dist-info/WHEEL
log_request_id-0.1.1.dist-info/METADATA
log_request_id-0.1.1.dist-info/RECORD
