Metadata-Version: 2.1
Name: log-request-id
Version: 0.1.1
Summary: Log-Request-ID is extension for handling request-ID in logging.
License: MIT
Author: kuzxnia
Author-email: kacper.kuzniarski@gmail.com
Requires-Python: >=3.6,<4.0
Classifier: License :: OSI Approved :: MIT License
Classifier: Programming Language :: Python :: 3
Classifier: Programming Language :: Python :: 3.6
Classifier: Programming Language :: Python :: 3.7
Classifier: Programming Language :: Python :: 3.8
Classifier: Programming Language :: Python :: 3.9
Classifier: Programming Language :: Python :: 3.10
Classifier: Programming Language :: Python :: 3.11
